artist/__init__.py
artist/accessor.py
artist/utils.py
icon_artist-0.0.1.dist-info/METADATA
icon_artist-0.0.1.dist-info/WHEEL
icon_artist-0.0.1.dist-info/top_level.txt
icon_artist-0.0.1.dist-info/RECORD
