Metadata-Version: 2.1
Name: icon-artist
Version: 0.0.1
Summary: Post-processing and plotting ICON-ART output in python
Home-page: https://github.com/pankajkarman/ARTist
Author: Pankaj Kumar
Author-email: pankaj.kmr1990@gmail.com
License: MIT
Requires-Dist: matplotlib
Requires-Dist: numpy
Requires-Dist: scipy
Requires-Dist: pandas
Requires-Dist: xarray
